examples/__init__.py
examples/header_factory.py
examples/software.py
examples/test_query_invoice_data.py
examples/test_token_exchange.py
ois_api_client/Client.py
ois_api_client/__init__.py
ois_api_client/constants.py
ois_api_client/deserialize_invoice.py
ois_api_client/header_factory.py
ois_api_client/custom_dto/RangeDate.py
ois_api_client/custom_dto/RangeMonetary.py
ois_api_client/custom_dto/__init__.py
ois_api_client/deserialization/__init__.py
ois_api_client/deserialization/create_enum.py
ois_api_client/deserialization/decode_invoice_data.py
ois_api_client/exceptions/GeneralError.py
ois_api_client/exceptions/__init__.py
ois_api_client/serialization/__init__.py
ois_api_client/serialization/build_request_signature.py
ois_api_client/serialization/hash_password.py
ois_api_client/serialization/serialize_additional_query_params.py
ois_api_client/serialization/serialize_basic_online_invoice_request.py
ois_api_client/serialization/serialize_element.py
ois_api_client/serialization/serialize_header.py
ois_api_client/serialization/serialize_mandatory_query_params.py
ois_api_client/serialization/serialize_query_invoice_data_request.py
ois_api_client/serialization/serialize_query_invoice_digest_request.py
ois_api_client/serialization/serialize_relational_query_params.py
ois_api_client/serialization/serialize_software.py
ois_api_client/serialization/serialize_token_exchange_request.py
ois_api_client/serialization/serialize_transaction_query_params.py
ois_api_client/serialization/serialize_user.py
ois_api_client/v2_0/__init__.py
ois_api_client/v2_0/namespaces.py
ois_api_client/v2_0/deserialization/__init__.py
ois_api_client/v2_0/deserialization/deserialize_additional_data.py
ois_api_client/v2_0/deserialization/deserialize_additional_query_params.py
ois_api_client/v2_0/deserialization/deserialize_address.py
ois_api_client/v2_0/deserialization/deserialize_aggregate_invoice_line_data.py
ois_api_client/v2_0/deserialization/deserialize_aircraft.py
ois_api_client-0.3.6.dist-info/LICENSE
ois_api_client-0.3.6.dist-info/METADATA
ois_api_client-0.3.6.dist-info/WHEEL
ois_api_client-0.3.6.dist-info/top_level.txt
ois_api_client-0.3.6.dist-info/RECORD
