Metadata-Version: 2.1
Name: ois-api-client
Version: 0.3.6
Summary: A python client library for the hungarian Online Invoice System API
Home-page: https://github.com/peterkulik/ois_api_client
Author: Peter Kulik
Author-email: peter@importas.dev
License: UNKNOWN
Platform: UNKNOWN
Classifier: Development Status :: 3 - Alpha
Classifier: Intended Audience :: Developers
Classifier: Operating System :: OS Independent
Classifier: Programming Language :: Python
Classifier: Programming Language :: Python :: 3.7
Classifier: Programming Language :: Python :: 3.8
Classifier: Programming Language :: Python :: 3.9
Classifier: Topic :: Office/Business
Classifier: Topic :: Software Development :: Libraries
Classifier: Topic :: Software Development :: Libraries :: Python Modules
Classifier: License :: OSI Approved :: MIT License
Requires-Python: >=3.7.0
Requires-Dist: requests
